{
  "pass": true,
  "overall_score": 7,
  "dimensions": {
    "syntax": {
      "score": 10,
      "pass": true,
      "issues": []
    },
    "layout": {
      "score": 9,
      "pass": true,
      "issues": []
    },
    "content_accuracy": {
      "score": 10,
      "pass": true,
      "issues": []
    },
    "chart_type_appropriateness": {
      "score": 9,
      "pass": true,
      "issues": []
    },
    "information_completeness": {
      "score": 10,
      "pass": true,
      "issues": []
    },
    "aesthetics": {
      "score": 6,
      "pass": true,
      "issues": [
        "TikTok标签橙色(#FF9800)在白色背景上对比度不足(WCAG AA 2.16:1)",
        "Kuaishou标签绿色(#4CAF50)在白色背景上对比度不足(WCAG AA 2.78:1)"
      ]
    },
    "creativity_density": {
      "score": 5,
      "pass": true,
      "issues": [
        "装饰元素中等(emoji+渐变+箭头+底部点睛)，缺少趣味细节或科普小知识"
      ]
    }
  },
  "needs_regeneration": false,
  "regeneration_focus": [],
  "specific_suggestions": [
    {
      "target": "TikTok标签文本 \"📱 TikTok\"",
      "issue": "橙色文本(#FF9800)在白色背景上对比度不足（2.16:1），不符合WCAG AA标准",
      "suggestion": "将文本颜色改为更深的橙色（如 #E65100）或添加白色背景框，也可考虑在柱体底部添加深色背景标签",
      "priority": "high"
    },
    {
      "target": "Kuaishou标签文本 \"🤳 Kuaishou\"",
      "issue": "绿色文本(#4CAF50)在白色背景上对比度不足（2.78:1），不符合WCAG AA标准",
      "suggestion": "将文本颜色改为更深的绿色（如 #1B5E20）或添加白色背景框",
      "priority": "high"
    },
    {
      "target": "倍数关系箭头（YouTube→TikTok）",
      "issue": "路径曲线较复杂，箭头指向可能不够精确，影响视觉清晰度",
      "suggestion": "改用直线或更简洁的贝塞尔曲线，确保箭头准确指向TikTok柱体顶部左侧",
      "priority": "medium"
    }
  ],
  "summary": "SVG整体质量较好，主要问题在于两个平台标签的文本对比度不足（橙色和绿色在白色背景上），需增强可读性。箭头路径可优化为更直观的直线。其他维度均通过，无需完全重生成。"
}